scrapy_requests_manipulate/__init__.py
scrapy_requests_manipulate/__version__.py
scrapy_requests_manipulate/downloaderMiddleware.py
scrapy_requests_manipulate/settings.py
scrapy_requests_manipulate-0.0.2.dist-info/LICENSE
scrapy_requests_manipulate-0.0.2.dist-info/METADATA
scrapy_requests_manipulate-0.0.2.dist-info/WHEEL
scrapy_requests_manipulate-0.0.2.dist-info/top_level.txt
scrapy_requests_manipulate-0.0.2.dist-info/RECORD
