Metadata-Version: 2.1
Name: scrapy-requests-manipulate
Version: 0.0.2
Summary: requests downloader middleware for scrapy, send request by requests.
Home-page: https://github.com/dylankeepon/ScrapyRequestsMiddleware.git
Author: Dylan Chen
Author-email: dylankeep@163.com
License: MIT
Classifier: Environment :: Web Environment
Classifier: Intended Audience :: Developers
Classifier: Natural Language :: English
Classifier: Operating System :: Unix
Classifier: Operating System :: MacOS :: MacOS X
Classifier: Operating System :: Microsoft :: Windows
Classifier: License :: OSI Approved :: MIT License
Classifier: Programming Language :: Python
Classifier: Programming Language :: Python :: 3
Classifier: Programming Language :: Python :: Implementation :: CPython
Classifier: Programming Language :: Python :: Implementation :: PyPy
Classifier: Topic :: Internet :: WWW/HTTP
Classifier: Topic :: Software Development :: Libraries
Requires-Python: >=3.7.0
License-File: LICENSE
Requires-Dist: scrapy (>=2.0.0)
Requires-Dist: requests (>=2.0.0)
